jvmcoredump/cli.py
jvmcoredump/debugger.py
jvmcoredump/gdb.py
jvmcoredump/syms.py
jvmcoredump_gczuczy-0.5.1.dist-info/LICENSE
jvmcoredump_gczuczy-0.5.1.dist-info/METADATA
jvmcoredump_gczuczy-0.5.1.dist-info/WHEEL
jvmcoredump_gczuczy-0.5.1.dist-info/entry_points.txt
jvmcoredump_gczuczy-0.5.1.dist-info/top_level.txt
jvmcoredump_gczuczy-0.5.1.dist-info/RECORD
