Metadata-Version: 2.1
Name: jvmcoredump-gczuczy
Version: 0.5.1
Summary: Provides valid coredumps for JVMs stuck in GC loops
Home-page: https://github.com/gczuczy/jvmcoredump
Author: Gergely Czuczy
Author-email: gergely.czuczy@harmless.hu
Project-URL: Bug Tracker, https://github.com/gczuczy/jvmcoredump/issues
Classifier: Programming Language :: Python :: 3
Classifier: License :: OSI Approved :: BSD License
Classifier: Operating System :: OS Independent
Classifier: Intended Audience :: Developers
Classifier: Topic :: Software Development :: Debuggers
Requires-Python: >=3.7
License-File: LICENSE
Requires-Dist: python-gdb-ctrl
Requires-Dist: pexpect
Requires-Dist: pyyaml
